README.md
setup.py
python_common_tools/__init__.py
python_common_tools/auth.py
python_common_tools/autoreload.py
python_common_tools/cache.py
python_common_tools/compress.py
python_common_tools/db.py
python_common_tools/linux.py
python_common_tools/python.py
python_common_tools/queue.py
python_common_tools/test.py
python_common_tools.egg-info/PKG-INFO
python_common_tools.egg-info/SOURCES.txt
python_common_tools.egg-info/dependency_links.txt
python_common_tools.egg-info/entry_points.txt
python_common_tools.egg-info/top_level.txt