Metadata-Version: 2.1
Name: python-common-tools
Version: 2.6
Summary: python common tools
Home-page: https://github.com/CheungChan/python_common_tools
Author: chenzhang
Author-email: 1377699408@qq.com
License: UNKNOWN
Platform: UNKNOWN
Requires-Python: >3.5.0
